{"findings":[{"id":"BH-UNSAFE-0001","file":"src/bug_hunter/languages.rs","line":105,"column":null,"title":"Transmute in unsafe block","description":"std::mem::transmute bypasses type safety; high-priority fuzzing target","severity":"Critical","category":"MemorySafety","suspiciousness":0.9,"discovered_by":"Fuzz","evidence":[{"evidence_type":"FuzzingCrash","description":"transmute","data":"N/A"}],"suggested_fix":null,"related":[],"regression_risk":null,"blame_author":null,"blame_commit":null,"blame_date":null},{"id":"BH-UNSAFE-0002","file":"src/bug_hunter/mod.rs","line":860,"column":null,"title":"Transmute in unsafe block","description":"std::mem::transmute bypasses type safety; high-priority fuzzing target","severity":"Critical","category":"MemorySafety","suspiciousness":0.9,"discovered_by":"Fuzz","evidence":[{"evidence_type":"FuzzingCrash","description":"transmute","data":"N/A"}],"suggested_fix":null,"related":[],"regression_risk":null,"blame_author":null,"blame_commit":null,"blame_date":null},{"id":"BH-UNSAFE-0003","file":"src/bug_hunter/mod.rs","line":873,"column":null,"title":"Transmute in unsafe block","description":"std::mem::transmute bypasses type safety; high-priority fuzzing target","severity":"Critical","category":"MemorySafety","suspiciousness":0.9,"discovered_by":"Fuzz","evidence":[{"evidence_type":"FuzzingCrash","description":"transmute","data":"N/A"}],"suggested_fix":null,"related":[],"regression_risk":null,"blame_author":null,"blame_commit":null,"blame_date":null},{"id":"BH-UNSAFE-0004","file":"src/bug_hunter/mod.rs","line":1142,"column":null,"title":"Pointer dereference in unsafe block","description":"Unsafe block starting at line 1140; potential fuzzing target","severity":"High","category":"MemorySafety","suspiciousness":0.75,"discovered_by":"Fuzz","evidence":[{"evidence_type":"FuzzingCrash","description":"pointer_deref","data":"N/A"}],"suggested_fix":null,"related":[],"regression_risk":null,"blame_author":null,"blame_commit":null,"blame_date":null},{"id":"BH-UNSAFE-0005","file":"src/bug_hunter/patterns.rs","line":8,"column":null,"title":"Transmute in unsafe block","description":"std::mem::transmute bypasses type safety; high-priority fuzzing target","severity":"Critical","category":"MemorySafety","suspiciousness":0.9,"discovered_by":"Fuzz","evidence":[{"evidence_type":"FuzzingCrash","description":"transmute","data":"N/A"}],"suggested_fix":null,"related":[],"regression_risk":null,"blame_author":null,"blame_commit":null,"blame_date":null},{"id":"BH-UNSAFE-0006","file":"src/bug_hunter/patterns.rs","line":354,"column":null,"title":"Transmute in unsafe block","description":"std::mem::transmute bypasses type safety; high-priority fuzzing target","severity":"Critical","category":"MemorySafety","suspiciousness":0.9,"discovered_by":"Fuzz","evidence":[{"evidence_type":"FuzzingCrash","description":"transmute","data":"N/A"}],"suggested_fix":null,"related":[],"regression_risk":null,"blame_author":null,"blame_commit":null,"blame_date":null},{"id":"BH-UNSAFE-0007","file":"src/oracle/rag/falsification.rs","line":547,"column":null,"title":"Pointer dereference in unsafe block","description":"Unsafe block starting at line 547; potential fuzzing target","severity":"High","category":"MemorySafety","suspiciousness":0.75,"discovered_by":"Fuzz","evidence":[{"evidence_type":"FuzzingCrash","description":"pointer_deref","data":"N/A"}],"suggested_fix":null,"related":[],"regression_risk":null,"blame_author":null,"blame_commit":null,"blame_date":null},{"id":"BH-UNSAFE-0008","file":"src/oracle/rag/quantization/simd.rs","line":125,"column":null,"title":"Pointer dereference in unsafe block","description":"Unsafe block starting at line 116; potential fuzzing target","severity":"High","category":"MemorySafety","suspiciousness":0.75,"discovered_by":"Fuzz","evidence":[{"evidence_type":"FuzzingCrash","description":"pointer_deref","data":"N/A"}],"suggested_fix":null,"related":[],"regression_risk":null,"blame_author":null,"blame_commit":null,"blame_date":null},{"id":"BH-UNSAFE-0009","file":"src/oracle/rag/quantization/simd.rs","line":126,"column":null,"title":"Pointer dereference in unsafe block","description":"Unsafe block starting at line 116; potential fuzzing target","severity":"High","category":"MemorySafety","suspiciousness":0.75,"discovered_by":"Fuzz","evidence":[{"evidence_type":"FuzzingCrash","description":"pointer_deref","data":"N/A"}],"suggested_fix":null,"related":[],"regression_risk":null,"blame_author":null,"blame_commit":null,"blame_date":null},{"id":"BH-UNSAFE-0010","file":"src/oracle/rag/quantization/simd.rs","line":171,"column":null,"title":"Pointer dereference in unsafe block","description":"Unsafe block starting at line 162; potential fuzzing target","severity":"High","category":"MemorySafety","suspiciousness":0.75,"discovered_by":"Fuzz","evidence":[{"evidence_type":"FuzzingCrash","description":"pointer_deref","data":"N/A"}],"suggested_fix":null,"related":[],"regression_risk":null,"blame_author":null,"blame_commit":null,"blame_date":null},{"id":"BH-UNSAFE-0011","file":"src/oracle/rag/quantization/simd.rs","line":172,"column":null,"title":"Pointer dereference in unsafe block","description":"Unsafe block starting at line 162; potential fuzzing target","severity":"High","category":"MemorySafety","suspiciousness":0.75,"discovered_by":"Fuzz","evidence":[{"evidence_type":"FuzzingCrash","description":"pointer_deref","data":"N/A"}],"suggested_fix":null,"related":[],"regression_risk":null,"blame_author":null,"blame_commit":null,"blame_date":null},{"id":"BH-FUZZ-NOTARGETS","file":"./Cargo.toml","line":1,"column":null,"title":"No fuzz directory found","description":"Create fuzz targets for 6 identified unsafe blocks","severity":"Medium","category":"ConfigurationErrors","suspiciousness":0.4,"discovered_by":"Fuzz","evidence":[],"suggested_fix":null,"related":[],"regression_risk":null,"blame_author":null,"blame_commit":null,"blame_date":null}],"mode":"Fuzz","config_hash":"9703cf02a573ed6a"}